antishlopcli/__init__.py
antishlopcli/agent.py
antishlopcli/antishlop.py
antishlopcli/config.py
antishlopcli/prompts.py
antishlopcli/ui.py
antishlopcli-1.1.8.dist-info/licenses/LICENSE
antishlopcli-1.1.8.dist-info/METADATA
antishlopcli-1.1.8.dist-info/WHEEL
antishlopcli-1.1.8.dist-info/entry_points.txt
antishlopcli-1.1.8.dist-info/top_level.txt
antishlopcli-1.1.8.dist-info/RECORD
