Metadata-Version: 2.4
Name: antishlopcli
Version: 1.1.8
Summary: AI-Powered Security Vulnerability Scanner with Enhanced UI
Author: itscool2b
Classifier: Programming Language :: Python :: 3
Classifier: License :: OSI Approved :: MIT License
Classifier: Operating System :: OS Independent
Requires-Python: >=3.8
License-File: LICENSE
Requires-Dist: openai
Requires-Dist: colorama
Requires-Dist: rich
Requires-Dist: python-dotenv
Requires-Dist: langchain==0.3.23
Requires-Dist: langchain-openai==0.3.12
Requires-Dist: langgraph==0.2.67
Requires-Dist: typing-extensions
Dynamic: author
Dynamic: classifier
Dynamic: description
Dynamic: description-content-type
Dynamic: license-file
Dynamic: requires-dist
Dynamic: requires-python
Dynamic: summary
